<?xml version="1.0" encoding="windows-1252"?>
<XMI xmi.version="1.1" xmlns:UML="omg.org/UML1.3">
	<XMI.header>
		<XMI.documentation>
			<XMI.exporter>Enterprise Architect</XMI.exporter>
			<XMI.exporterVersion>2.5</XMI.exporterVersion>
		</XMI.documentation>
	</XMI.header>
	<XMI.content>
		<UML:Model name="EA Model" xmi.id="MX_EAID_37CCCCC3_BA92_4612_A721_FE34C5D19E49">
			<UML:Namespace.ownedElement>
				<UML:Class name="EARootClass" xmi.id="EAID_11111111_5487_4080_A7F4_41526CB0AA00" isRoot="true" isLeaf="false" isAbstract="false"/>
				<UML:Package name="Area" xmi.id="EAPK_37CCCCC3_BA92_4612_A721_FE34C5D19E49" isRoot="false" isLeaf="false" isAbstract="false" visibility="public">
					<UML:ModelElement.taggedValue>
						<UML:TaggedValue tag="parent" value="EAPK_83105B1A_E9CA_48dd_81D8_E234A9506167"/>
						<UML:TaggedValue tag="created" value="2016-03-23 17:30:12"/>
						<UML:TaggedValue tag="modified" value="2016-03-23 17:30:27"/>
						<UML:TaggedValue tag="iscontrolled" value="TRUE"/>
						<UML:TaggedValue tag="xmlpath" value="eaF\FE34C5D19E49.xml"/>
						<UML:TaggedValue tag="version" value="1.0"/>
						<UML:TaggedValue tag="isprotected" value="FALSE"/>
						<UML:TaggedValue tag="usedtd" value="FALSE"/>
						<UML:TaggedValue tag="owner" value="&#23376;&#29275;&#36830;"/>
						<UML:TaggedValue tag="xmiver" value="Enterprise Architect XMI/UML 1.3"/>
						<UML:TaggedValue tag="logxml" value="FALSE"/>
						<UML:TaggedValue tag="packageFlags" value="Recurse=0;VCCFG=LZR_JS;CRC=0;"/>
						<UML:TaggedValue tag="batchsave" value="0"/>
						<UML:TaggedValue tag="batchload" value="0"/>
						<UML:TaggedValue tag="phase" value="1.0"/>
						<UML:TaggedValue tag="status" value="Proposed"/>
						<UML:TaggedValue tag="author" value="&#23376;&#29275;&#36830;"/>
						<UML:TaggedValue tag="alias" value="&#21306;&#22495;"/>
						<UML:TaggedValue tag="complexity" value="1"/>
						<UML:TaggedValue tag="ea_stype" value="Public"/>
						<UML:TaggedValue tag="tpos" value="0"/>
						<UML:TaggedValue tag="gentype" value="JS_LZR"/>
					</UML:ModelElement.taggedValue>
					<UML:Namespace.ownedElement>
						<UML:Class name="EmAreaLevel" xmi.id="EAID_02DE3E6C_D2AE_4ee5_B4BE_6AF5210DDC27" visibility="public" namespace="EAPK_37CCCCC3_BA92_4612_A721_FE34C5D19E49" isRoot="false" isLeaf="false" isAbstract="false" isActive="false">
							<UML:ModelElement.taggedValue>
								<UML:TaggedValue tag="isSpecification" value="false"/>
								<UML:TaggedValue tag="ea_stype" value="Class"/>
								<UML:TaggedValue tag="ea_ntype" value="0"/>
								<UML:TaggedValue tag="version" value="1.0"/>
								<UML:TaggedValue tag="package" value="EAPK_37CCCCC3_BA92_4612_A721_FE34C5D19E49"/>
								<UML:TaggedValue tag="date_created" value="2016-03-23 17:39:05"/>
								<UML:TaggedValue tag="date_modified" value="2016-03-28 15:04:18"/>
								<UML:TaggedValue tag="genfile" value="F:\GitLib\LZR_JS\src\LZR\JS\LZR\Pro\Gis\Area\EmAreaLevel.js"/>
								<UML:TaggedValue tag="gentype" value="JS_LZR"/>
								<UML:TaggedValue tag="tagged" value="0"/>
								<UML:TaggedValue tag="package_name" value="Area"/>
								<UML:TaggedValue tag="phase" value="1.0"/>
								<UML:TaggedValue tag="alias" value="&#21306;&#22495;&#32423;&#21035;&#26522;&#20030;"/>
								<UML:TaggedValue tag="author" value="&#23376;&#29275;&#36830;"/>
								<UML:TaggedValue tag="complexity" value="1"/>
								<UML:TaggedValue tag="status" value="Proposed"/>
								<UML:TaggedValue tag="tpos" value="0"/>
								<UML:TaggedValue tag="ea_localid" value="201"/>
								<UML:TaggedValue tag="ea_eleType" value="element"/>
								<UML:TaggedValue tag="eventflags" value="OBJ=f8d3;"/>
								<UML:TaggedValue tag="style" value="BackColor=-1;BorderColor=-1;BorderWidth=-1;FontColor=-1;VSwimLanes=1;HSwimLanes=1;BorderStyle=0;"/>
							</UML:ModelElement.taggedValue>
							<UML:Classifier.feature>
								<UML:Operation name="hdObj_" visibility="public" ownerScope="instance" isQuery="false" concurrency="sequential">
									<UML:ModelElement.taggedValue>
										<UML:TaggedValue tag="const" value="false"/>
										<UML:TaggedValue tag="synchronised" value="0"/>
										<UML:TaggedValue tag="concurrency" value="Sequential"/>
										<UML:TaggedValue tag="position" value="0"/>
										<UML:TaggedValue tag="returnarray" value="0"/>
										<UML:TaggedValue tag="pure" value="0"/>
										<UML:TaggedValue tag="ea_guid" value="{5E84D1A3-2A7A-4d50-903E-B678A82C7AEB}"/>
										<UML:TaggedValue tag="ea_localid" value="436"/>
										<UML:TaggedValue tag="style" value="&#23545;&#26500;&#36896;&#21442;&#25968;&#30340;&#29305;&#27530;&#22788;&#29702;"/>
									</UML:ModelElement.taggedValue>
									<UML:BehavioralFeature.parameter>
										<UML:Parameter kind="return" visibility="public">
											<UML:Parameter.type>
												<UML:Classifier xmi.idref="eaxmiid0"/>
											</UML:Parameter.type>
											<UML:ModelElement.taggedValue>
												<UML:TaggedValue tag="pos" value="0"/>
												<UML:TaggedValue tag="const" value="0"/>
												<UML:TaggedValue tag="ea_guid" value="{RETURNID-2A7A-4d50-903E-B678A82C7AEB}"/>
											</UML:ModelElement.taggedValue>
											<UML:Parameter.defaultValue>
												<UML:Expression/>
											</UML:Parameter.defaultValue>
										</UML:Parameter>
										<UML:Parameter name="obj" kind="in" visibility="public">
											<UML:Parameter.type>
												<UML:Classifier xmi.idref="eaxmiid1"/>
											</UML:Parameter.type>
											<UML:ModelElement.taggedValue>
												<UML:TaggedValue tag="pos" value="0"/>
												<UML:TaggedValue tag="type" value="Object"/>
												<UML:TaggedValue tag="const" value="0"/>
												<UML:TaggedValue tag="styleex" value="alias=&#26500;&#36896;&#21442;&#25968;;"/>
												<UML:TaggedValue tag="ea_guid" value="{55F8B225-AA96-4cd8-AA35-331376E531ED}"/>
											</UML:ModelElement.taggedValue>
											<UML:Parameter.defaultValue>
												<UML:Expression/>
											</UML:Parameter.defaultValue>
										</UML:Parameter>
									</UML:BehavioralFeature.parameter>
								</UML:Operation>
							</UML:Classifier.feature>
						</UML:Class>
						<UML:Generalization subtype="EAID_02DE3E6C_D2AE_4ee5_B4BE_6AF5210DDC27" supertype="EAID_637ED555_9E33_4f9a_B63C_FA09B5573887" xmi.id="EAID_0048250F_43C1_43d6_AD22_BB8AE81FD326" visibility="public">
							<UML:ModelElement.taggedValue>
								<UML:TaggedValue tag="style" value="3"/>
								<UML:TaggedValue tag="ea_type" value="Generalization"/>
								<UML:TaggedValue tag="direction" value="Source -&gt; Destination"/>
								<UML:TaggedValue tag="linemode" value="3"/>
								<UML:TaggedValue tag="linecolor" value="-1"/>
								<UML:TaggedValue tag="linewidth" value="0"/>
								<UML:TaggedValue tag="seqno" value="0"/>
								<UML:TaggedValue tag="headStyle" value="0"/>
								<UML:TaggedValue tag="lineStyle" value="0"/>
								<UML:TaggedValue tag="ea_localid" value="279"/>
								<UML:TaggedValue tag="ea_sourceName" value="EmAreaLevel"/>
								<UML:TaggedValue tag="ea_targetName" value="Enum"/>
								<UML:TaggedValue tag="ea_sourceType" value="Class"/>
								<UML:TaggedValue tag="ea_targetType" value="Class"/>
								<UML:TaggedValue tag="ea_sourceID" value="201"/>
								<UML:TaggedValue tag="ea_targetID" value="181"/>
								<UML:TaggedValue tag="src_visibility" value="Public"/>
								<UML:TaggedValue tag="src_aggregation" value="0"/>
								<UML:TaggedValue tag="src_isOrdered" value="false"/>
								<UML:TaggedValue tag="src_targetScope" value="instance"/>
								<UML:TaggedValue tag="src_changeable" value="none"/>
								<UML:TaggedValue tag="src_isNavigable" value="false"/>
								<UML:TaggedValue tag="src_containment" value="Unspecified"/>
								<UML:TaggedValue tag="src_style" value="Union=0;Derived=0;AllowDuplicates=0;"/>
								<UML:TaggedValue tag="dst_visibility" value="Public"/>
								<UML:TaggedValue tag="dst_aggregation" value="0"/>
								<UML:TaggedValue tag="dst_isOrdered" value="false"/>
								<UML:TaggedValue tag="dst_targetScope" value="instance"/>
								<UML:TaggedValue tag="dst_changeable" value="none"/>
								<UML:TaggedValue tag="dst_isNavigable" value="true"/>
								<UML:TaggedValue tag="dst_containment" value="Unspecified"/>
								<UML:TaggedValue tag="dst_style" value="Union=0;Derived=0;AllowDuplicates=0;"/>
								<UML:TaggedValue tag="privatedata5" value="SX=0;SY=0;EX=0;EY=0;EDGE=2;"/>
								<UML:TaggedValue tag="virtualInheritance" value="0"/>
							</UML:ModelElement.taggedValue>
						</UML:Generalization>
						<UML:Association xmi.id="EAID_2473C989_6060_47f1_A16E_B3243C4C4142" visibility="public" isRoot="false" isLeaf="false" isAbstract="false">
							<UML:ModelElement.taggedValue>
								<UML:TaggedValue tag="style" value="3"/>
								<UML:TaggedValue tag="ea_type" value="Aggregation"/>
								<UML:TaggedValue tag="direction" value="Source -&gt; Destination"/>
								<UML:TaggedValue tag="linemode" value="3"/>
								<UML:TaggedValue tag="linecolor" value="-1"/>
								<UML:TaggedValue tag="linewidth" value="0"/>
								<UML:TaggedValue tag="seqno" value="0"/>
								<UML:TaggedValue tag="subtype" value="Weak"/>
								<UML:TaggedValue tag="headStyle" value="0"/>
								<UML:TaggedValue tag="lineStyle" value="0"/>
								<UML:TaggedValue tag="ea_localid" value="252"/>
								<UML:TaggedValue tag="ea_sourceName" value="AreaLevel"/>
								<UML:TaggedValue tag="ea_targetName" value="EmAreaLevel"/>
								<UML:TaggedValue tag="ea_sourceType" value="Class"/>
								<UML:TaggedValue tag="ea_targetType" value="Class"/>
								<UML:TaggedValue tag="ea_sourceID" value="199"/>
								<UML:TaggedValue tag="ea_targetID" value="201"/>
								<UML:TaggedValue tag="privatedata5" value="SX=60;SY=2;EX=61;EY=2;EDGE=1;"/>
								<UML:TaggedValue tag="virtualInheritance" value="0"/>
								<UML:TaggedValue tag="lt" value="+station"/>
							</UML:ModelElement.taggedValue>
							<UML:Association.connection>
								<UML:AssociationEnd visibility="public" name="station" aggregation="none" isOrdered="false" targetScope="classifier" changeable="none" isNavigable="false" type="EAID_98B24A76_F5B4_4edc_B35D_944BBD2FE5EA">
									<UML:ModelElement.taggedValue>
										<UML:TaggedValue tag="description" value="&#31449;&#28857;"/>
										<UML:TaggedValue tag="containment" value="Unspecified"/>
										<UML:TaggedValue tag="sourcestyle" value="Union=0;Derived=0;AllowDuplicates=0;Owned=0;Navigable=Non-Navigable;alias=&#31449;&#28857;;"/>
										<UML:TaggedValue tag="ea_end" value="source"/>
										<UML:TaggedValue tag="LZR_initial" value="&lt;memo&gt;$ea_notes={&#xA;	id: 300,&#xA;	name: &quot;&#31449;&#28857;&quot;&#xA;}" xmi.id="EAID_7D147989_A1C2_48db_85F4_35682084034B"/>
									</UML:ModelElement.taggedValue>
								</UML:AssociationEnd>
								<UML:AssociationEnd visibility="public" aggregation="shared" isOrdered="false" targetScope="instance" changeable="none" isNavigable="true" type="EAID_02DE3E6C_D2AE_4ee5_B4BE_6AF5210DDC27">
									<UML:ModelElement.taggedValue>
										<UML:TaggedValue tag="containment" value="Unspecified"/>
										<UML:TaggedValue tag="deststyle" value="Union=0;Derived=0;AllowDuplicates=0;Owned=0;Navigable=Navigable;"/>
										<UML:TaggedValue tag="ea_end" value="target"/>
									</UML:ModelElement.taggedValue>
								</UML:AssociationEnd>
							</UML:Association.connection>
						</UML:Association>
						<UML:Association xmi.id="EAID_2C98F836_C3EB_42a5_A571_D26B92EFA5D0" visibility="public" isRoot="false" isLeaf="false" isAbstract="false">
							<UML:ModelElement.taggedValue>
								<UML:TaggedValue tag="style" value="3"/>
								<UML:TaggedValue tag="ea_type" value="Aggregation"/>
								<UML:TaggedValue tag="direction" value="Source -&gt; Destination"/>
								<UML:TaggedValue tag="linemode" value="3"/>
								<UML:TaggedValue tag="linecolor" value="-1"/>
								<UML:TaggedValue tag="linewidth" value="0"/>
								<UML:TaggedValue tag="seqno" value="0"/>
								<UML:TaggedValue tag="subtype" value="Weak"/>
								<UML:TaggedValue tag="headStyle" value="0"/>
								<UML:TaggedValue tag="lineStyle" value="0"/>
								<UML:TaggedValue tag="ea_localid" value="251"/>
								<UML:TaggedValue tag="ea_sourceName" value="AreaLevel"/>
								<UML:TaggedValue tag="ea_targetName" value="EmAreaLevel"/>
								<UML:TaggedValue tag="ea_sourceType" value="Class"/>
								<UML:TaggedValue tag="ea_targetType" value="Class"/>
								<UML:TaggedValue tag="ea_sourceID" value="199"/>
								<UML:TaggedValue tag="ea_targetID" value="201"/>
								<UML:TaggedValue tag="privatedata5" value="SX=0;SY=0;EX=0;EY=0;EDGE=1;"/>
								<UML:TaggedValue tag="virtualInheritance" value="0"/>
								<UML:TaggedValue tag="lt" value="+city"/>
							</UML:ModelElement.taggedValue>
							<UML:Association.connection>
								<UML:AssociationEnd visibility="public" name="city" aggregation="none" isOrdered="false" targetScope="classifier" changeable="none" isNavigable="false" type="EAID_98B24A76_F5B4_4edc_B35D_944BBD2FE5EA">
									<UML:ModelElement.taggedValue>
										<UML:TaggedValue tag="description" value="&#24066;"/>
										<UML:TaggedValue tag="containment" value="Unspecified"/>
										<UML:TaggedValue tag="sourcestyle" value="Union=0;Derived=0;AllowDuplicates=0;Owned=0;Navigable=Non-Navigable;alias=&#24066;;"/>
										<UML:TaggedValue tag="ea_end" value="source"/>
										<UML:TaggedValue tag="LZR_initial" value="&lt;memo&gt;$ea_notes={&#xA;	id: 100,&#xA;	name: &quot;&#24066;&quot;&#xA;}" xmi.id="EAID_316A7EC9_F6AD_416c_95E2_15D598246426"/>
									</UML:ModelElement.taggedValue>
								</UML:AssociationEnd>
								<UML:AssociationEnd visibility="public" aggregation="shared" isOrdered="false" targetScope="instance" changeable="none" isNavigable="true" type="EAID_02DE3E6C_D2AE_4ee5_B4BE_6AF5210DDC27">
									<UML:ModelElement.taggedValue>
										<UML:TaggedValue tag="containment" value="Unspecified"/>
										<UML:TaggedValue tag="deststyle" value="Union=0;Derived=0;AllowDuplicates=0;Owned=0;Navigable=Navigable;"/>
										<UML:TaggedValue tag="ea_end" value="target"/>
									</UML:ModelElement.taggedValue>
								</UML:AssociationEnd>
							</UML:Association.connection>
						</UML:Association>
						<UML:Association xmi.id="EAID_483A7E40_2DB5_43e1_BFB4_A299719A090C" visibility="public" isRoot="false" isLeaf="false" isAbstract="false">
							<UML:ModelElement.taggedValue>
								<UML:TaggedValue tag="style" value="3"/>
								<UML:TaggedValue tag="ea_type" value="Aggregation"/>
								<UML:TaggedValue tag="direction" value="Source -&gt; Destination"/>
								<UML:TaggedValue tag="linemode" value="3"/>
								<UML:TaggedValue tag="linecolor" value="-1"/>
								<UML:TaggedValue tag="linewidth" value="0"/>
								<UML:TaggedValue tag="seqno" value="0"/>
								<UML:TaggedValue tag="subtype" value="Weak"/>
								<UML:TaggedValue tag="headStyle" value="0"/>
								<UML:TaggedValue tag="lineStyle" value="0"/>
								<UML:TaggedValue tag="ea_localid" value="250"/>
								<UML:TaggedValue tag="ea_sourceName" value="AreaLevel"/>
								<UML:TaggedValue tag="ea_targetName" value="EmAreaLevel"/>
								<UML:TaggedValue tag="ea_sourceType" value="Class"/>
								<UML:TaggedValue tag="ea_targetType" value="Class"/>
								<UML:TaggedValue tag="ea_sourceID" value="199"/>
								<UML:TaggedValue tag="ea_targetID" value="201"/>
								<UML:TaggedValue tag="privatedata5" value="SX=-60;SY=2;EX=-59;EY=2;EDGE=1;"/>
								<UML:TaggedValue tag="virtualInheritance" value="0"/>
								<UML:TaggedValue tag="lt" value="+prvn"/>
							</UML:ModelElement.taggedValue>
							<UML:Association.connection>
								<UML:AssociationEnd visibility="public" name="prvn" aggregation="none" isOrdered="false" targetScope="classifier" changeable="none" isNavigable="false" type="EAID_98B24A76_F5B4_4edc_B35D_944BBD2FE5EA">
									<UML:ModelElement.taggedValue>
										<UML:TaggedValue tag="description" value="&#30465;"/>
										<UML:TaggedValue tag="containment" value="Unspecified"/>
										<UML:TaggedValue tag="sourcestyle" value="Union=0;Derived=0;AllowDuplicates=0;Owned=0;Navigable=Non-Navigable;alias=&#30465;;"/>
										<UML:TaggedValue tag="ea_end" value="source"/>
										<UML:TaggedValue tag="LZR_initial" value="&lt;memo&gt;$ea_notes={&#xA;	id: 30,&#xA;	name: &quot;&#30465;&quot;&#xA;}" xmi.id="EAID_5A293E15_A03C_4545_A1E6_6BDE1E90D555"/>
									</UML:ModelElement.taggedValue>
								</UML:AssociationEnd>
								<UML:AssociationEnd visibility="public" aggregation="shared" isOrdered="false" targetScope="instance" changeable="none" isNavigable="true" type="EAID_02DE3E6C_D2AE_4ee5_B4BE_6AF5210DDC27">
									<UML:ModelElement.taggedValue>
										<UML:TaggedValue tag="containment" value="Unspecified"/>
										<UML:TaggedValue tag="deststyle" value="Union=0;Derived=0;AllowDuplicates=0;Owned=0;Navigable=Navigable;"/>
										<UML:TaggedValue tag="ea_end" value="target"/>
									</UML:ModelElement.taggedValue>
								</UML:AssociationEnd>
							</UML:Association.connection>
						</UML:Association>
						<UML:Association xmi.id="EAID_8CD51A0F_0EF9_42ca_8CAD_982475564655" visibility="public" isRoot="false" isLeaf="false" isAbstract="false">
							<UML:ModelElement.taggedValue>
								<UML:TaggedValue tag="style" value="3"/>
								<UML:TaggedValue tag="ea_type" value="Aggregation"/>
								<UML:TaggedValue tag="direction" value="Source -&gt; Destination"/>
								<UML:TaggedValue tag="linemode" value="3"/>
								<UML:TaggedValue tag="linecolor" value="-1"/>
								<UML:TaggedValue tag="linewidth" value="0"/>
								<UML:TaggedValue tag="seqno" value="0"/>
								<UML:TaggedValue tag="subtype" value="Weak"/>
								<UML:TaggedValue tag="headStyle" value="0"/>
								<UML:TaggedValue tag="lineStyle" value="0"/>
								<UML:TaggedValue tag="ea_localid" value="249"/>
								<UML:TaggedValue tag="ea_sourceName" value="EmAreaLevel"/>
								<UML:TaggedValue tag="ea_targetName" value="Area"/>
								<UML:TaggedValue tag="ea_sourceType" value="Class"/>
								<UML:TaggedValue tag="ea_targetType" value="Class"/>
								<UML:TaggedValue tag="ea_sourceID" value="201"/>
								<UML:TaggedValue tag="ea_targetID" value="196"/>
								<UML:TaggedValue tag="privatedata5" value="SX=0;SY=0;EX=0;EY=0;EDGE=1;"/>
								<UML:TaggedValue tag="virtualInheritance" value="0"/>
								<UML:TaggedValue tag="lt" value="+emLevel"/>
							</UML:ModelElement.taggedValue>
							<UML:Association.connection>
								<UML:AssociationEnd visibility="public" name="emLevel" aggregation="none" isOrdered="false" targetScope="instance" changeable="none" isNavigable="false" type="EAID_02DE3E6C_D2AE_4ee5_B4BE_6AF5210DDC27">
									<UML:ModelElement.taggedValue>
										<UML:TaggedValue tag="description" value="&#21306;&#22495;&#32423;&#21035;"/>
										<UML:TaggedValue tag="containment" value="Unspecified"/>
										<UML:TaggedValue tag="sourcestyle" value="Union=0;Derived=0;AllowDuplicates=0;Owned=0;Navigable=Non-Navigable;alias=&#21306;&#22495;&#32423;&#21035;;"/>
										<UML:TaggedValue tag="ea_end" value="source"/>
									</UML:ModelElement.taggedValue>
								</UML:AssociationEnd>
								<UML:AssociationEnd visibility="public" aggregation="shared" isOrdered="false" targetScope="instance" changeable="none" isNavigable="true" type="EAID_C0FE5963_8CD4_4c4c_8B55_00556FB4948B">
									<UML:ModelElement.taggedValue>
										<UML:TaggedValue tag="containment" value="Unspecified"/>
										<UML:TaggedValue tag="deststyle" value="Union=0;Derived=0;AllowDuplicates=0;Owned=0;Navigable=Navigable;"/>
										<UML:TaggedValue tag="ea_end" value="target"/>
									</UML:ModelElement.taggedValue>
								</UML:AssociationEnd>
							</UML:Association.connection>
						</UML:Association>
						<UML:Association xmi.id="EAID_F3AB9F78_C35F_4cfa_AEFA_11C30F273686" visibility="public" isRoot="false" isLeaf="false" isAbstract="false">
							<UML:ModelElement.taggedValue>
								<UML:TaggedValue tag="style" value="3"/>
								<UML:TaggedValue tag="ea_type" value="Aggregation"/>
								<UML:TaggedValue tag="direction" value="Source -&gt; Destination"/>
								<UML:TaggedValue tag="linemode" value="3"/>
								<UML:TaggedValue tag="linecolor" value="-1"/>
								<UML:TaggedValue tag="linewidth" value="0"/>
								<UML:TaggedValue tag="seqno" value="0"/>
								<UML:TaggedValue tag="subtype" value="Weak"/>
								<UML:TaggedValue tag="headStyle" value="0"/>
								<UML:TaggedValue tag="lineStyle" value="0"/>
								<UML:TaggedValue tag="ea_localid" value="312"/>
								<UML:TaggedValue tag="ea_sourceName" value="AreaLevel"/>
								<UML:TaggedValue tag="ea_targetName" value="EmAreaLevel"/>
								<UML:TaggedValue tag="ea_sourceType" value="Class"/>
								<UML:TaggedValue tag="ea_targetType" value="Class"/>
								<UML:TaggedValue tag="ea_sourceID" value="199"/>
								<UML:TaggedValue tag="ea_targetID" value="201"/>
								<UML:TaggedValue tag="privatedata5" value="SX=-89;SY=2;EX=-88;EY=2;EDGE=1;"/>
								<UML:TaggedValue tag="virtualInheritance" value="0"/>
								<UML:TaggedValue tag="lt" value="+emnull"/>
							</UML:ModelElement.taggedValue>
							<UML:Association.connection>
								<UML:AssociationEnd visibility="public" name="emnull" aggregation="none" isOrdered="false" targetScope="classifier" changeable="none" isNavigable="false" type="EAID_98B24A76_F5B4_4edc_B35D_944BBD2FE5EA">
									<UML:ModelElement.taggedValue>
										<UML:TaggedValue tag="description" value="&#26080;"/>
										<UML:TaggedValue tag="containment" value="Unspecified"/>
										<UML:TaggedValue tag="sourcestyle" value="Union=0;Derived=0;AllowDuplicates=0;Owned=0;Navigable=Non-Navigable;alias=&#26080;;"/>
										<UML:TaggedValue tag="ea_end" value="source"/>
									</UML:ModelElement.taggedValue>
								</UML:AssociationEnd>
								<UML:AssociationEnd visibility="public" aggregation="shared" isOrdered="false" targetScope="instance" changeable="none" isNavigable="true" type="EAID_02DE3E6C_D2AE_4ee5_B4BE_6AF5210DDC27">
									<UML:ModelElement.taggedValue>
										<UML:TaggedValue tag="containment" value="Unspecified"/>
										<UML:TaggedValue tag="deststyle" value="Union=0;Derived=0;AllowDuplicates=0;Owned=0;Navigable=Navigable;"/>
										<UML:TaggedValue tag="ea_end" value="target"/>
									</UML:ModelElement.taggedValue>
								</UML:AssociationEnd>
							</UML:Association.connection>
						</UML:Association>
						<UML:Class name="AreaLevel" xmi.id="EAID_98B24A76_F5B4_4edc_B35D_944BBD2FE5EA" visibility="public" namespace="EAPK_37CCCCC3_BA92_4612_A721_FE34C5D19E49" isRoot="false" isLeaf="false" isAbstract="false" isActive="false">
							<UML:ModelElement.taggedValue>
								<UML:TaggedValue tag="isSpecification" value="false"/>
								<UML:TaggedValue tag="ea_stype" value="Class"/>
								<UML:TaggedValue tag="ea_ntype" value="0"/>
								<UML:TaggedValue tag="version" value="1.0"/>
								<UML:TaggedValue tag="package" value="EAPK_37CCCCC3_BA92_4612_A721_FE34C5D19E49"/>
								<UML:TaggedValue tag="date_created" value="2016-03-23 17:39:01"/>
								<UML:TaggedValue tag="date_modified" value="2016-03-24 16:14:44"/>
								<UML:TaggedValue tag="genfile" value="F:\GitLib\LZR_JS\src\LZR\JS\LZR\Pro\Gis\Area\AreaLevel.js"/>
								<UML:TaggedValue tag="gentype" value="JS_LZR"/>
								<UML:TaggedValue tag="tagged" value="0"/>
								<UML:TaggedValue tag="package_name" value="Area"/>
								<UML:TaggedValue tag="phase" value="1.0"/>
								<UML:TaggedValue tag="alias" value="&#21306;&#22495;&#32423;&#21035;"/>
								<UML:TaggedValue tag="author" value="&#23376;&#29275;&#36830;"/>
								<UML:TaggedValue tag="complexity" value="1"/>
								<UML:TaggedValue tag="status" value="Proposed"/>
								<UML:TaggedValue tag="tpos" value="0"/>
								<UML:TaggedValue tag="ea_localid" value="199"/>
								<UML:TaggedValue tag="ea_eleType" value="element"/>
								<UML:TaggedValue tag="eventflags" value="OBJ=199d;"/>
								<UML:TaggedValue tag="style" value="BackColor=-1;BorderColor=-1;BorderWidth=-1;FontColor=-1;VSwimLanes=1;HSwimLanes=1;BorderStyle=0;"/>
							</UML:ModelElement.taggedValue>
							<UML:Classifier.feature>
								<UML:Attribute name="id" changeable="none" visibility="private" ownerScope="instance" targetScope="instance">
									<UML:Attribute.initialValue>
										<UML:Expression body="0"/>
									</UML:Attribute.initialValue>
									<UML:StructuralFeature.type>
										<UML:Classifier xmi.idref="eaxmiid2"/>
									</UML:StructuralFeature.type>
									<UML:ModelElement.taggedValue>
										<UML:TaggedValue tag="type" value="int"/>
										<UML:TaggedValue tag="derived" value="0"/>
										<UML:TaggedValue tag="containment" value="Not Specified"/>
										<UML:TaggedValue tag="ordered" value="0"/>
										<UML:TaggedValue tag="collection" value="false"/>
										<UML:TaggedValue tag="position" value="0"/>
										<UML:TaggedValue tag="lowerBound" value="1"/>
										<UML:TaggedValue tag="upperBound" value="1"/>
										<UML:TaggedValue tag="duplicates" value="0"/>
										<UML:TaggedValue tag="ea_guid" value="{592F922B-A07B-49f1-B8A1-7FA0BEA4A5AB}"/>
										<UML:TaggedValue tag="ea_localid" value="192"/>
										<UML:TaggedValue tag="styleex" value="IsLiteral=0;volatile=0;"/>
										<UML:TaggedValue tag="style" value="&#32423;&#21035;&#32534;&#21495;"/>
									</UML:ModelElement.taggedValue>
								</UML:Attribute>
								<UML:Attribute name="name" changeable="none" visibility="private" ownerScope="instance" targetScope="instance">
									<UML:Attribute.initialValue>
										<UML:Expression body="&quot;&quot;"/>
									</UML:Attribute.initialValue>
									<UML:StructuralFeature.type>
										<UML:Classifier xmi.idref="eaxmiid3"/>
									</UML:StructuralFeature.type>
									<UML:ModelElement.taggedValue>
										<UML:TaggedValue tag="type" value="string"/>
										<UML:TaggedValue tag="derived" value="0"/>
										<UML:TaggedValue tag="containment" value="Not Specified"/>
										<UML:TaggedValue tag="ordered" value="0"/>
										<UML:TaggedValue tag="collection" value="false"/>
										<UML:TaggedValue tag="position" value="1"/>
										<UML:TaggedValue tag="lowerBound" value="1"/>
										<UML:TaggedValue tag="upperBound" value="1"/>
										<UML:TaggedValue tag="duplicates" value="0"/>
										<UML:TaggedValue tag="ea_guid" value="{226024E1-34E7-414b-8772-885CE016E7A3}"/>
										<UML:TaggedValue tag="ea_localid" value="193"/>
										<UML:TaggedValue tag="styleex" value="IsLiteral=0;volatile=0;"/>
										<UML:TaggedValue tag="style" value="&#21517;&#31216;"/>
									</UML:ModelElement.taggedValue>
								</UML:Attribute>
								<UML:Operation name="init_" visibility="public" ownerScope="instance" isQuery="false" concurrency="sequential">
									<UML:ModelElement.taggedValue>
										<UML:TaggedValue tag="const" value="false"/>
										<UML:TaggedValue tag="synchronised" value="0"/>
										<UML:TaggedValue tag="concurrency" value="Sequential"/>
										<UML:TaggedValue tag="position" value="0"/>
										<UML:TaggedValue tag="returnarray" value="0"/>
										<UML:TaggedValue tag="pure" value="0"/>
										<UML:TaggedValue tag="ea_guid" value="{B5225A89-63E7-4050-8F4C-F1E189B934BC}"/>
										<UML:TaggedValue tag="ea_localid" value="433"/>
										<UML:TaggedValue tag="style" value="&#26500;&#36896;&#22120;"/>
										<UML:TaggedValue tag="LZR_code" value="&lt;memo&gt;" xmi.id="EAID_E126981B_57EC_48cd_92A3_1BD5DF17BFB7">
											<XMI.extension xmi.extender="Enterprise Architect 2.5">
												<UML:Comment name="if (obj) {&#xA;		LZR.setObj (this, obj);&#xA;		this.hdObj_(obj);&#xA;	}"/>
											</XMI.extension>
										</UML:TaggedValue>
									</UML:ModelElement.taggedValue>
									<UML:BehavioralFeature.parameter>
										<UML:Parameter kind="return" visibility="public">
											<UML:Parameter.type>
												<UML:Classifier xmi.idref="eaxmiid0"/>
											</UML:Parameter.type>
											<UML:ModelElement.taggedValue>
												<UML:TaggedValue tag="pos" value="0"/>
												<UML:TaggedValue tag="const" value="0"/>
												<UML:TaggedValue tag="ea_guid" value="{RETURNID-63E7-4050-8F4C-F1E189B934BC}"/>
											</UML:ModelElement.taggedValue>
											<UML:Parameter.defaultValue>
												<UML:Expression/>
											</UML:Parameter.defaultValue>
										</UML:Parameter>
										<UML:Parameter name="obj" kind="in" visibility="public">
											<UML:Parameter.type>
												<UML:Classifier xmi.idref="eaxmiid1"/>
											</UML:Parameter.type>
											<UML:ModelElement.taggedValue>
												<UML:TaggedValue tag="pos" value="0"/>
												<UML:TaggedValue tag="type" value="Object"/>
												<UML:TaggedValue tag="const" value="0"/>
												<UML:TaggedValue tag="styleex" value="alias=&#26500;&#36896;&#21442;&#25968;;"/>
												<UML:TaggedValue tag="ea_guid" value="{1E118B7A-6413-4c9c-99AD-573569E41438}"/>
											</UML:ModelElement.taggedValue>
											<UML:Parameter.defaultValue>
												<UML:Expression/>
											</UML:Parameter.defaultValue>
										</UML:Parameter>
									</UML:BehavioralFeature.parameter>
								</UML:Operation>
								<UML:Operation name="hdObj_" visibility="public" ownerScope="instance" isQuery="false" concurrency="sequential">
									<UML:ModelElement.taggedValue>
										<UML:TaggedValue tag="const" value="false"/>
										<UML:TaggedValue tag="synchronised" value="0"/>
										<UML:TaggedValue tag="concurrency" value="Sequential"/>
										<UML:TaggedValue tag="position" value="1"/>
										<UML:TaggedValue tag="returnarray" value="0"/>
										<UML:TaggedValue tag="pure" value="0"/>
										<UML:TaggedValue tag="ea_guid" value="{4BD81720-77B9-4a32-B788-86FF58A7A65E}"/>
										<UML:TaggedValue tag="ea_localid" value="434"/>
										<UML:TaggedValue tag="style" value="&#23545;&#26500;&#36896;&#21442;&#25968;&#30340;&#29305;&#27530;&#22788;&#29702;"/>
									</UML:ModelElement.taggedValue>
									<UML:BehavioralFeature.parameter>
										<UML:Parameter kind="return" visibility="public">
											<UML:Parameter.type>
												<UML:Classifier xmi.idref="eaxmiid0"/>
											</UML:Parameter.type>
											<UML:ModelElement.taggedValue>
												<UML:TaggedValue tag="pos" value="0"/>
												<UML:TaggedValue tag="const" value="0"/>
												<UML:TaggedValue tag="ea_guid" value="{RETURNID-77B9-4a32-B788-86FF58A7A65E}"/>
											</UML:ModelElement.taggedValue>
											<UML:Parameter.defaultValue>
												<UML:Expression/>
											</UML:Parameter.defaultValue>
										</UML:Parameter>
										<UML:Parameter name="obj" kind="in" visibility="public">
											<UML:Parameter.type>
												<UML:Classifier xmi.idref="eaxmiid1"/>
											</UML:Parameter.type>
											<UML:ModelElement.taggedValue>
												<UML:TaggedValue tag="pos" value="0"/>
												<UML:TaggedValue tag="type" value="Object"/>
												<UML:TaggedValue tag="const" value="0"/>
												<UML:TaggedValue tag="styleex" value="alias=&#26500;&#36896;&#21442;&#25968;;"/>
												<UML:TaggedValue tag="ea_guid" value="{1E1A1206-9093-413b-8C92-18E85E3DA681}"/>
											</UML:ModelElement.taggedValue>
											<UML:Parameter.defaultValue>
												<UML:Expression/>
											</UML:Parameter.defaultValue>
										</UML:Parameter>
									</UML:BehavioralFeature.parameter>
								</UML:Operation>
							</UML:Classifier.feature>
						</UML:Class>
					</UML:Namespace.ownedElement>
				</UML:Package>
				<UML:DataType xmi.id="eaxmiid0" visibility="private" isRoot="false" isLeaf="false" isAbstract="false"/>
				<UML:DataType xmi.id="eaxmiid3" name="string" visibility="private" isRoot="false" isLeaf="false" isAbstract="false"/>
				<UML:DataType xmi.id="eaxmiid2" name="int" visibility="private" isRoot="false" isLeaf="false" isAbstract="false"/>
				<UML:DataType xmi.id="eaxmiid1" name="Object" visibility="private" isRoot="false" isLeaf="false" isAbstract="false"/>
			</UML:Namespace.ownedElement>
		</UML:Model>
		<UML:Diagram name="&#21306;&#22495;" xmi.id="EAID_D0F556EB_92FD_4d8d_BD85_DF337BF1FF0D" diagramType="ClassDiagram" owner="EAPK_37CCCCC3_BA92_4612_A721_FE34C5D19E49" toolName="Enterprise Architect 2.5">
			<UML:ModelElement.taggedValue>
				<UML:TaggedValue tag="version" value="1.0"/>
				<UML:TaggedValue tag="author" value="&#23376;&#29275;&#36830;"/>
				<UML:TaggedValue tag="created_date" value="2016-03-23 17:30:18"/>
				<UML:TaggedValue tag="modified_date" value="2016-03-28 15:03:43"/>
				<UML:TaggedValue tag="package" value="EAPK_37CCCCC3_BA92_4612_A721_FE34C5D19E49"/>
				<UML:TaggedValue tag="type" value="Logical"/>
				<UML:TaggedValue tag="swimlanes" value="locked=false;orientation=0;width=0;inbar=false;names=false;color=-1;bold=false;fcol=0;tcol=-1;ofCol=-1;hl=1;cls=0;"/>
				<UML:TaggedValue tag="matrixitems" value="locked=false;matrixactive=false;swimlanesactive=true;kanbanactive=false;width=1;"/>
				<UML:TaggedValue tag="ea_localid" value="40"/>
				<UML:TaggedValue tag="EAStyle" value="ShowPrivate=1;ShowProtected=1;ShowPublic=1;HideRelationships=0;Locked=0;Border=1;HighlightForeign=1;PackageContents=1;SequenceNotes=0;ScalePrintImage=0;PPgs.cx=0;PPgs.cy=0;DocSize.cx=827;DocSize.cy=1169;ShowDetails=0;Orientation=P;Zoom=150;ShowTags=0;OpParams=2;VisibleAttributeDetail=0;ShowOpRetType=1;ShowIcons=1;CollabNums=0;HideProps=0;ShowReqs=0;ShowCons=0;PaperSize=9;HideParents=0;UseAlias=1;HideAtts=0;HideOps=0;HideStereo=0;HideElemStereo=0;ShowTests=0;ShowMaint=0;ConnectorNotation=UML 2.1;ExplicitNavigability=0;AdvancedElementProps=1;AdvancedFeatureProps=1;AdvancedConnectorProps=1;ShowNotes=0;SuppressBrackets=0;SuppConnectorLabels=0;PrintPageHeadFoot=0;ShowAsList=0;"/>
				<UML:TaggedValue tag="styleex" value="SaveTag=FA21376C;ExcludeRTF=0;DocAll=0;HideQuals=0;AttPkg=1;ShowTests=0;ShowMaint=0;SuppressFOC=1;MatrixActive=0;SwimlanesActive=1;KanbanActive=0;MatrixLineWidth=1;MatrixLocked=0;TConnectorNotation=UML 2.1;TExplicitNavigability=0;AdvancedElementProps=1;AdvancedFeatureProps=1;AdvancedConnectorProps=1;ProfileData=;MDGDgm=;STBLDgm=;ShowNotes=0;VisibleAttributeDetail=0;ShowOpRetType=1;SuppressBrackets=0;SuppConnectorLabels=0;PrintPageHeadFoot=0;ShowAsList=0;SuppressedCompartments=;"/>
			</UML:ModelElement.taggedValue>
			<UML:Diagram.element>
				<UML:DiagramElement geometry="Left=465;Top=326;Right=929;Bottom=440;" subject="EAID_27FC4AAA_2AC6_4edc_AFC6_F3BDA993200C" seqno="1" style="DUID=50E41697;NSL=0;BCol=-1;BFol=-1;LCol=-1;LWth=-1;fontsz=0;bold=0;black=0;italic=0;ul=0;charset=0;pitch=0;"/>
				<UML:DiagramElement geometry="Left=453;Top=493;Right=684;Bottom=651;" subject="EAID_637ED555_9E33_4f9a_B63C_FA09B5573887" seqno="2" style="DUID=3C8F92BA;NSL=0;BCol=-1;BFol=-1;LCol=-1;LWth=-1;fontsz=0;bold=0;black=0;italic=0;ul=0;charset=0;pitch=0;"/>
				<UML:DiagramElement geometry="Left=144;Top=675;Right=354;Bottom=771;" subject="EAID_98B24A76_F5B4_4edc_B35D_944BBD2FE5EA" seqno="3" style="DUID=4290B260;NSL=0;BCol=-1;BFol=-1;LCol=-1;LWth=-1;fontsz=0;bold=0;black=0;italic=0;ul=0;charset=0;pitch=0;"/>
				<UML:DiagramElement geometry="Left=143;Top=539;Right=353;Bottom=609;" subject="EAID_02DE3E6C_D2AE_4ee5_B4BE_6AF5210DDC27" seqno="4" style="DUID=32832381;NSL=0;BFol=-1;LCol=-1;LWth=-1;fontsz=0;bold=0;black=0;italic=0;ul=0;charset=0;pitch=0;BCol=-1;"/>
				<UML:DiagramElement geometry="Left=83;Top=33;Right=418;Bottom=272;" subject="EAID_973E00AF_A272_40e8_B359_6747C5F1ABD8" seqno="5" style="DUID=614FFE89;NSL=0;BCol=-1;BFol=-1;LCol=-1;LWth=-1;fontsz=0;bold=0;black=0;italic=0;ul=0;charset=0;pitch=0;"/>
				<UML:DiagramElement geometry="Left=143;Top=337;Right=353;Bottom=433;" subject="EAID_C0FE5963_8CD4_4c4c_8B55_00556FB4948B" seqno="6" style="DUID=9A856484;NSL=0;BFol=-1;LCol=-1;LWth=-1;fontsz=0;bold=0;black=0;italic=0;ul=0;charset=0;pitch=0;BCol=-1;"/>
				<UML:DiagramElement geometry="SX=0;SY=0;EX=0;EY=0;Path=;" subject="EAID_C350513E_DFD6_45d8_976C_D7456D01FD2C" style=";Hidden=0;"/>
				<UML:DiagramElement geometry="SX=0;SY=0;EX=0;EY=0;EDGE=1;$LLB=;LLT=;LMT=;LMB=;LRT=;LRB=;IRHS=;ILHS=;Path=;" subject="EAID_2DF6E611_8034_4010_A04C_6D57E7BACBE0" style="Mode=3;EOID=614FFE89;SOID=9A856484;Color=-1;LWidth=0;Hidden=0;"/>
				<UML:DiagramElement geometry="SX=-89;SY=2;EX=-88;EY=2;EDGE=1;$LLB=;LLT=CX=10:CY=13:OX=0:OY=0:HDN=0:BLD=0:ITA=0:UND=0:CLR=-1:ALN=0:DIR=0:ROT=0;LMT=;LMB=;LRT=;LRB=;IRHS=;ILHS=;Path=;" subject="EAID_F3AB9F78_C35F_4cfa_AEFA_11C30F273686" style="Mode=3;EOID=32832381;SOID=4290B260;Color=-1;LWidth=0;Hidden=0;"/>
				<UML:DiagramElement geometry="SX=0;SY=0;EX=0;EY=0;EDGE=4;$LLB=CX=6:CY=13:OX=0:OY=0:HDN=0:BLD=0:ITA=0:UND=0:CLR=-1:ALN=0:DIR=0:ROT=0;LLT=CX=50:CY=13:OX=-5:OY=1:HDN=0:BLD=0:ITA=0:UND=0:CLR=-1:ALN=0:DIR=0:ROT=0;LMT=;LMB=;LRT=;LRB=;IRHS=;ILHS=;Path=;" subject="EAID_3A5EA9C2_5655_4a31_BD6D_14150725CF16" style="Mode=3;EOID=9A856484;SOID=50E41697;Color=-1;LWidth=0;Hidden=0;"/>
				<UML:DiagramElement geometry="SX=0;SY=0;EX=0;EY=0;EDGE=2;$LLB=;LLT=;LMT=;LMB=;LRT=;LRB=;IRHS=;ILHS=;Path=;" subject="EAID_0048250F_43C1_43d6_AD22_BB8AE81FD326" style="Mode=3;EOID=3C8F92BA;SOID=32832381;Color=-1;LWidth=0;Hidden=0;"/>
				<UML:DiagramElement geometry="SX=60;SY=2;EX=61;EY=2;EDGE=1;$LLB=;LLT=CX=20:CY=13:OX=-1:OY=0:HDN=0:BLD=0:ITA=0:UND=0:CLR=-1:ALN=0:DIR=0:ROT=0;LMT=;LMB=;LRT=;LRB=;IRHS=;ILHS=;Path=;" subject="EAID_2473C989_6060_47f1_A16E_B3243C4C4142" style="Mode=3;EOID=32832381;SOID=4290B260;Color=-1;LWidth=0;Hidden=0;"/>
				<UML:DiagramElement geometry="SX=0;SY=0;EX=0;EY=0;EDGE=1;$LLB=;LLT=CX=10:CY=13:OX=0:OY=0:HDN=0:BLD=0:ITA=0:UND=0:CLR=-1:ALN=0:DIR=0:ROT=0;LMT=;LMB=;LRT=;LRB=;IRHS=;ILHS=;Path=;" subject="EAID_2C98F836_C3EB_42a5_A571_D26B92EFA5D0" style="Mode=3;EOID=32832381;SOID=4290B260;Color=-1;LWidth=0;Hidden=0;"/>
				<UML:DiagramElement geometry="SX=-60;SY=2;EX=-59;EY=2;EDGE=1;$LLB=;LLT=CX=10:CY=13:OX=-2:OY=0:HDN=0:BLD=0:ITA=0:UND=0:CLR=-1:ALN=0:DIR=0:ROT=0;LMT=;LMB=;LRT=;LRB=;IRHS=;ILHS=;Path=;" subject="EAID_483A7E40_2DB5_43e1_BFB4_A299719A090C" style="Mode=3;EOID=32832381;SOID=4290B260;Color=-1;LWidth=0;Hidden=0;"/>
				<UML:DiagramElement geometry="SX=0;SY=0;EX=0;EY=0;EDGE=1;$LLB=;LLT=CX=40:CY=13:OX=-3:OY=1:HDN=0:BLD=0:ITA=0:UND=0:CLR=-1:ALN=0:DIR=0:ROT=0;LMT=;LMB=;LRT=;LRB=;IRHS=;ILHS=;Path=;" subject="EAID_8CD51A0F_0EF9_42ca_8CAD_982475564655" style="Mode=3;EOID=9A856484;SOID=32832381;Color=-1;LWidth=0;Hidden=0;"/>
				<UML:DiagramElement geometry="SCTR=1;SCME=1;SX=0;SY=0;EX=0;EY=0;EDGE=3;SCTR.LEFT=417;SCTR.TOP=-302;SCTR.RIGHT=696;SCTR.BOTTOM=-271;$LLB=;LLT=;LMT=;LMB=;LRT=;LRB=;IRHS=;ILHS=;Path=417:-272$417:-302$696:-302$696:-271$418:-271$;" subject="EAID_EA9523F5_6093_4af3_B46A_A11073449DF0" style="Mode=3;EOID=614FFE89;SOID=614FFE89;Color=-1;LWidth=0;Hidden=1;"/>
			</UML:Diagram.element>
		</UML:Diagram>
		<UML:DiagramElement geometry="Left=334;Top=49;Right=464;Bottom=129;" subject="EAID_37CCCCC3_BA92_4612_A721_FE34C5D19E49" seqno="1" style=" DUID=16C9B9BF;">
			<UML:ModelElement.taggedValue>
				<UML:TaggedValue tag="diagram_guid" value="EAID_91E87407_21AE_49d0_A7BD_CBF59C1B912E"/>
			</UML:ModelElement.taggedValue>
		</UML:DiagramElement>
	</XMI.content>
	<XMI.difference/>
	<XMI.extensions xmi.extender="Enterprise Architect 2.5">
		<EAStub xmi.id="EAID_637ED555_9E33_4f9a_B63C_FA09B5573887" name="Enum" UMLType="Class"/>
		<EAModel.paramSub/>
		<EAStub xmi.id="EAID_C0FE5963_8CD4_4c4c_8B55_00556FB4948B" name="Area" UMLType="Class"/>
	</XMI.extensions>
</XMI>
